[
  {
    "match_number": 1,
    "date": "2026-06-11",
    "kickoff_utc": "2026-06-11T19:00:00Z",
    "group": "A",
    "home_team": "Mexico",
    "away_team": "South Africa",
    "expected_goals_home": 2.03,
    "expected_goals_away": 0.45,
    "prob_win_home": 0.749,
    "prob_draw": 0.179,
    "prob_win_away": 0.071,
    "prob_over_1_5": 0.71,
    "prob_over_2_5": 0.453,
    "prob_btts": 0.317,
    "predicted_score_home": 2,
    "predicted_score_away": 0,
    "is_over_1_5_alert": 0,
    "is_over_2_5_alert": 0,
    "real_score_home": 2,
    "real_score_away": 0
  },
  {
    "match_number": 2,
    "date": "2026-06-11",
    "kickoff_utc": "2026-06-12T02:00:00Z",
    "group": "A",
    "home_team": "South Korea",
    "away_team": "Czech Republic",
    "expected_goals_home": 2.31,
    "expected_goals_away": 1.29,
    "prob_win_home": 0.602,
    "prob_draw": 0.194,
    "prob_win_away": 0.204,
    "prob_over_1_5": 0.874,
    "prob_over_2_5": 0.697,
    "prob_btts": 0.652,
    "predicted_score_home": 2,
    "predicted_score_away": 1,
    "is_over_1_5_alert": 1,
    "is_over_2_5_alert": 0,
    "real_score_home": 2,
    "real_score_away": 1
  },
  {
    "match_number": 3,
    "date": "2026-06-12",
    "kickoff_utc": "2026-06-12T19:00:00Z",
    "group": "B",
    "home_team": "Canada",
    "away_team": "Bosnia and Herzegovina",
    "expected_goals_home": 3.32,
    "expected_goals_away": 1.0,
    "prob_win_home": 0.813,
    "prob_draw": 0.111,
    "prob_win_away": 0.076,
    "prob_over_1_5": 0.927,
    "prob_over_2_5": 0.802,
    "prob_btts": 0.607,
    "predicted_score_home": 3,
    "predicted_score_away": 0,
    "is_over_1_5_alert": 1,
    "is_over_2_5_alert": 1,
    "real_score_home": 1,
    "real_score_away": 1
  },
  {
    "match_number": 4,
    "date": "2026-06-12",
    "kickoff_utc": "2026-06-13T01:00:00Z",
    "group": "D",
    "home_team": "United States",
    "away_team": "Paraguay",
    "expected_goals_home": 2.06,
    "expected_goals_away": 0.99,
    "prob_win_home": 0.62,
    "prob_draw": 0.206,
    "prob_win_away": 0.174,
    "prob_over_1_5": 0.808,
    "prob_over_2_5": 0.588,
    "prob_btts": 0.549,
    "predicted_score_home": 2,
    "predicted_score_away": 0,
    "is_over_1_5_alert": 0,
    "is_over_2_5_alert": 0,
    "real_score_home": 4,
    "real_score_away": 1
  },
  {
    "match_number": 5,
    "date": "2026-06-13",
    "kickoff_utc": "2026-06-14T01:00:00Z",
    "group": "C",
    "home_team": "Haiti",
    "away_team": "Scotland",
    "expected_goals_home": 1.55,
    "expected_goals_away": 3.03,
    "prob_win_home": 0.172,
    "prob_draw": 0.155,
    "prob_win_away": 0.673,
    "prob_over_1_5": 0.942,
    "prob_over_2_5": 0.834,
    "prob_btts": 0.749,
    "predicted_score_home": 1,
    "predicted_score_away": 3,
    "is_over_1_5_alert": 1,
    "is_over_2_5_alert": 1,
    "real_score_home": 0,
    "real_score_away": 1
  },
  {
    "match_number": 6,
    "date": "2026-06-13",
    "kickoff_utc": "2026-06-14T04:00:00Z",
    "group": "D",
    "home_team": "Australia",
    "away_team": "Turkey",
    "expected_goals_home": 1.54,
    "expected_goals_away": 1.49,
    "prob_win_home": 0.391,
    "prob_draw": 0.241,
    "prob_win_away": 0.368,
    "prob_over_1_5": 0.806,
    "prob_over_2_5": 0.584,
    "prob_btts": 0.609,
    "predicted_score_home": 1,
    "predicted_score_away": 1,
    "is_over_1_5_alert": 0,
    "is_over_2_5_alert": 0,
    "real_score_home": 2,
    "real_score_away": 0
  },
  {
    "match_number": 7,
    "date": "2026-06-13",
    "kickoff_utc": "2026-06-13T22:00:00Z",
    "group": "C",
    "home_team": "Brazil",
    "away_team": "Morocco",
    "expected_goals_home": 0.91,
    "expected_goals_away": 1.49,
    "prob_win_home": 0.23,
    "prob_draw": 0.262,
    "prob_win_away": 0.508,
    "prob_over_1_5": 0.691,
    "prob_over_2_5": 0.429,
    "prob_btts": 0.462,
    "predicted_score_home": 0,
    "predicted_score_away": 1,
    "is_over_1_5_alert": 0,
    "is_over_2_5_alert": 0,
    "real_score_home": 1,
    "real_score_away": 1
  },
  {
    "match_number": 8,
    "date": "2026-06-13",
    "kickoff_utc": "2026-06-13T19:00:00Z",
    "group": "B",
    "home_team": "Qatar",
    "away_team": "Switzerland",
    "expected_goals_home": 0.85,
    "expected_goals_away": 5.05,
    "prob_win_home": 0.017,
    "prob_draw": 0.036,
    "prob_win_away": 0.946,
    "prob_over_1_5": 0.947,
    "prob_over_2_5": 0.9,
    "prob_btts": 0.549,
    "predicted_score_home": 0,
    "predicted_score_away": 5,
    "is_over_1_5_alert": 1,
    "is_over_2_5_alert": 1,
    "real_score_home": 1,
    "real_score_away": 1
  },
  {
    "match_number": 9,
    "date": "2026-06-14",
    "kickoff_utc": "2026-06-14T23:00:00Z",
    "group": "E",
    "home_team": "Ivory Coast",
    "away_team": "Ecuador",
    "expected_goals_home": 0.65,
    "expected_goals_away": 0.48,
    "prob_win_home": 0.337,
    "prob_draw": 0.432,
    "prob_win_away": 0.231,
    "prob_over_1_5": 0.313,
    "prob_over_2_5": 0.106,
    "prob_btts": 0.183,
    "predicted_score_home": 0,
    "predicted_score_away": 0,
    "is_over_1_5_alert": 0,
    "is_over_2_5_alert": 0,
    "real_score_home": 1,
    "real_score_away": 0
  },
  {
    "match_number": 10,
    "date": "2026-06-14",
    "kickoff_utc": "2026-06-14T17:00:00Z",
    "group": "E",
    "home_team": "Germany",
    "away_team": "Curaçao",
    "expected_goals_home": 6.26,
    "expected_goals_away": 0.93,
    "prob_win_home": 0.972,
    "prob_draw": 0.02,
    "prob_win_away": 0.009,
    "prob_over_1_5": 0.891,
    "prob_over_2_5": 0.871,
    "prob_btts": 0.541,
    "predicted_score_home": 6,
    "predicted_score_away": 0,
    "is_over_1_5_alert": 1,
    "is_over_2_5_alert": 1,
    "real_score_home": 7,
    "real_score_away": 1
  },
  {
    "match_number": 11,
    "date": "2026-06-14",
    "kickoff_utc": "2026-06-14T20:00:00Z",
    "group": "F",
    "home_team": "Netherlands",
    "away_team": "Japan",
    "expected_goals_home": 1.77,
    "expected_goals_away": 2.19,
    "prob_win_home": 0.316,
    "prob_draw": 0.204,
    "prob_win_away": 0.479,
    "prob_over_1_5": 0.905,
    "prob_over_2_5": 0.755,
    "prob_btts": 0.736,
    "predicted_score_home": 1,
    "predicted_score_away": 2,
    "is_over_1_5_alert": 1,
    "is_over_2_5_alert": 1,
    "real_score_home": 2,
    "real_score_away": 2
  },
  {
    "match_number": 12,
    "date": "2026-06-14",
    "kickoff_utc": "2026-06-15T02:00:00Z",
    "group": "F",
    "home_team": "Sweden",
    "away_team": "Tunisia",
    "expected_goals_home": 3.19,
    "expected_goals_away": 1.79,
    "prob_win_home": 0.654,
    "prob_draw": 0.154,
    "prob_win_away": 0.192,
    "prob_over_1_5": 0.957,
    "prob_over_2_5": 0.872,
    "prob_btts": 0.797,
    "predicted_score_home": 3,
    "predicted_score_away": 1,
    "is_over_1_5_alert": 1,
    "is_over_2_5_alert": 1,
    "real_score_home": 5,
    "real_score_away": 1
  },
  {
    "match_number": 13,
    "date": "2026-06-15",
    "kickoff_utc": "2026-06-15T22:00:00Z",
    "group": "H",
    "home_team": "Saudi Arabia",
    "away_team": "Uruguay",
    "expected_goals_home": 0.5,
    "expected_goals_away": 1.87,
    "prob_win_home": 0.092,
    "prob_draw": 0.204,
    "prob_win_away": 0.705,
    "prob_over_1_5": 0.686,
    "prob_over_2_5": 0.424,
    "prob_btts": 0.335,
    "predicted_score_home": 0,
    "predicted_score_away": 1,
    "is_over_1_5_alert": 0,
    "is_over_2_5_alert": 0,
    "real_score_home": 1,
    "real_score_away": 1
  },
  {
    "match_number": 14,
    "date": "2026-06-15",
    "kickoff_utc": "2026-06-15T16:00:00Z",
    "group": "H",
    "home_team": "Spain",
    "away_team": "Cape Verde",
    "expected_goals_home": 4.09,
    "expected_goals_away": 0.46,
    "prob_win_home": 0.944,
    "prob_draw": 0.042,
    "prob_win_away": 0.014,
    "prob_over_1_5": 0.932,
    "prob_over_2_5": 0.823,
    "prob_btts": 0.36,
    "predicted_score_home": 4,
    "predicted_score_away": 0,
    "is_over_1_5_alert": 1,
    "is_over_2_5_alert": 1,
    "real_score_home": 0,
    "real_score_away": 0
  },
  {
    "match_number": 15,
    "date": "2026-06-15",
    "kickoff_utc": "2026-06-16T01:00:00Z",
    "group": "G",
    "home_team": "Iran",
    "away_team": "New Zealand",
    "expected_goals_home": 3.04,
    "expected_goals_away": 1.55,
    "prob_win_home": 0.676,
    "prob_draw": 0.155,
    "prob_win_away": 0.169,
    "prob_over_1_5": 0.942,
    "prob_over_2_5": 0.834,
    "prob_btts": 0.748,
    "predicted_score_home": 3,
    "predicted_score_away": 1,
    "is_over_1_5_alert": 1,
    "is_over_2_5_alert": 1,
    "real_score_home": 2,
    "real_score_away": 2
  },
  {
    "match_number": 16,
    "date": "2026-06-15",
    "kickoff_utc": "2026-06-15T19:00:00Z",
    "group": "G",
    "home_team": "Belgium",
    "away_team": "Egypt",
    "expected_goals_home": 2.09,
    "expected_goals_away": 0.94,
    "prob_win_home": 0.637,
    "prob_draw": 0.202,
    "prob_win_away": 0.161,
    "prob_over_1_5": 0.806,
    "prob_over_2_5": 0.584,
    "prob_btts": 0.535,
    "predicted_score_home": 2,
    "predicted_score_away": 0,
    "is_over_1_5_alert": 0,
    "is_over_2_5_alert": 0,
    "real_score_home": 1,
    "real_score_away": 1
  },
  {
    "match_number": 17,
    "date": "2026-06-16",
    "kickoff_utc": "2026-06-16T19:00:00Z",
    "group": "I",
    "home_team": "France",
    "away_team": "Senegal",
    "expected_goals_home": 2.44,
    "expected_goals_away": 1.32,
    "prob_win_home": 0.62,
    "prob_draw": 0.185,
    "prob_win_away": 0.194,
    "prob_over_1_5": 0.889,
    "prob_over_2_5": 0.724,
    "prob_btts": 0.669,
    "predicted_score_home": 2,
    "predicted_score_away": 1,
    "is_over_1_5_alert": 1,
    "is_over_2_5_alert": 1,
    "real_score_home": 3,
    "real_score_away": 1
  },
  {
    "match_number": 18,
    "date": "2026-06-16",
    "kickoff_utc": "2026-06-16T22:00:00Z",
    "group": "I",
    "home_team": "Iraq",
    "away_team": "Norway",
    "expected_goals_home": 0.81,
    "expected_goals_away": 6.23,
    "prob_win_home": 0.007,
    "prob_draw": 0.017,
    "prob_win_away": 0.976,
    "prob_over_1_5": 0.892,
    "prob_over_2_5": 0.87,
    "prob_btts": 0.499,
    "predicted_score_home": 0,
    "predicted_score_away": 6,
    "is_over_1_5_alert": 1,
    "is_over_2_5_alert": 1,
    "real_score_home": 1,
    "real_score_away": 4
  },
  {
    "match_number": 19,
    "date": "2026-06-16",
    "kickoff_utc": "2026-06-17T01:00:00Z",
    "group": "J",
    "home_team": "Argentina",
    "away_team": "Algeria",
    "expected_goals_home": 2.59,
    "expected_goals_away": 0.64,
    "prob_win_home": 0.792,
    "prob_draw": 0.138,
    "prob_win_away": 0.07,
    "prob_over_1_5": 0.832,
    "prob_over_2_5": 0.626,
    "prob_btts": 0.437,
    "predicted_score_home": 2,
    "predicted_score_away": 0,
    "is_over_1_5_alert": 0,
    "is_over_2_5_alert": 0,
    "real_score_home": 3,
    "real_score_away": 0
  },
  {
    "match_number": 20,
    "date": "2026-06-16",
    "kickoff_utc": "2026-06-17T04:00:00Z",
    "group": "J",
    "home_team": "Austria",
    "away_team": "Jordan",
    "expected_goals_home": 3.75,
    "expected_goals_away": 1.18,
    "prob_win_home": 0.829,
    "prob_draw": 0.098,
    "prob_win_away": 0.073,
    "prob_over_1_5": 0.952,
    "prob_over_2_5": 0.864,
    "prob_btts": 0.672,
    "predicted_score_home": 3,
    "predicted_score_away": 1,
    "is_over_1_5_alert": 1,
    "is_over_2_5_alert": 1,
    "real_score_home": 3,
    "real_score_away": 1
  },
  {
    "match_number": 21,
    "date": "2026-06-17",
    "kickoff_utc": "2026-06-17T23:00:00Z",
    "group": "L",
    "home_team": "Ghana",
    "away_team": "Panama",
    "expected_goals_home": 1.84,
    "expected_goals_away": 1.01,
    "prob_win_home": 0.569,
    "prob_draw": 0.227,
    "prob_win_away": 0.204,
    "prob_over_1_5": 0.776,
    "prob_over_2_5": 0.541,
    "prob_btts": 0.533,
    "predicted_score_home": 1,
    "predicted_score_away": 1,
    "is_over_1_5_alert": 0,
    "is_over_2_5_alert": 0,
    "real_score_home": 1,
    "real_score_away": 0
  },
  {
    "match_number": 22,
    "date": "2026-06-17",
    "kickoff_utc": "2026-06-17T20:00:00Z",
    "group": "L",
    "home_team": "England",
    "away_team": "Croatia",
    "expected_goals_home": 2.54,
    "expected_goals_away": 0.73,
    "prob_win_home": 0.765,
    "prob_draw": 0.149,
    "prob_win_away": 0.086,
    "prob_over_1_5": 0.838,
    "prob_over_2_5": 0.635,
    "prob_btts": 0.479,
    "predicted_score_home": 2,
    "predicted_score_away": 0,
    "is_over_1_5_alert": 0,
    "is_over_2_5_alert": 0,
    "real_score_home": 4,
    "real_score_away": 2
  },
  {
    "match_number": 23,
    "date": "2026-06-17",
    "kickoff_utc": "2026-06-17T17:00:00Z",
    "group": "K",
    "home_team": "Portugal",
    "away_team": "DR Congo",
    "expected_goals_home": 2.07,
    "expected_goals_away": 0.73,
    "prob_win_home": 0.686,
    "prob_draw": 0.194,
    "prob_win_away": 0.12,
    "prob_over_1_5": 0.768,
    "prob_over_2_5": 0.53,
    "prob_btts": 0.452,
    "predicted_score_home": 2,
    "predicted_score_away": 0,
    "is_over_1_5_alert": 0,
    "is_over_2_5_alert": 0,
    "real_score_home": 1,
    "real_score_away": 1
  },
  {
    "match_number": 24,
    "date": "2026-06-17",
    "kickoff_utc": "2026-06-18T02:00:00Z",
    "group": "K",
    "home_team": "Uzbekistan",
    "away_team": "Colombia",
    "expected_goals_home": 0.75,
    "expected_goals_away": 3.09,
    "prob_win_home": 0.059,
    "prob_draw": 0.109,
    "prob_win_away": 0.833,
    "prob_over_1_5": 0.895,
    "prob_over_2_5": 0.737,
    "prob_btts": 0.503,
    "predicted_score_home": 0,
    "predicted_score_away": 3,
    "is_over_1_5_alert": 1,
    "is_over_2_5_alert": 1,
    "real_score_home": 1,
    "real_score_away": 3
  },
  {
    "match_number": 25,
    "date": "2026-06-18",
    "kickoff_utc": "2026-06-18T16:00:00Z",
    "group": "A",
    "home_team": "Czech Republic",
    "away_team": "South Africa",
    "expected_goals_home": 1.87,
    "expected_goals_away": 1.37,
    "prob_win_home": 0.493,
    "prob_draw": 0.225,
    "prob_win_away": 0.281,
    "prob_over_1_5": 0.834,
    "prob_over_2_5": 0.628,
    "prob_btts": 0.63,
    "predicted_score_home": 1,
    "predicted_score_away": 1,
    "is_over_1_5_alert": 0,
    "is_over_2_5_alert": 0,
    "real_score_home": 1,
    "real_score_away": 1
  },
  {
    "match_number": 26,
    "date": "2026-06-18",
    "kickoff_utc": "2026-06-18T19:00:00Z",
    "group": "B",
    "home_team": "Switzerland",
    "away_team": "Bosnia and Herzegovina",
    "expected_goals_home": 3.49,
    "expected_goals_away": 1.2,
    "prob_win_home": 0.798,
    "prob_draw": 0.113,
    "prob_win_away": 0.089,
    "prob_over_1_5": 0.944,
    "prob_over_2_5": 0.843,
    "prob_btts": 0.675,
    "predicted_score_home": 3,
    "predicted_score_away": 1,
    "is_over_1_5_alert": 1,
    "is_over_2_5_alert": 1,
    "real_score_home": 4,
    "real_score_away": 1
  },
  {
    "match_number": 27,
    "date": "2026-06-18",
    "kickoff_utc": "2026-06-18T22:00:00Z",
    "group": "B",
    "home_team": "Canada",
    "away_team": "Qatar",
    "expected_goals_home": 4.8,
    "expected_goals_away": 0.71,
    "prob_win_home": 0.949,
    "prob_draw": 0.036,
    "prob_win_away": 0.015,
    "prob_over_1_5": 0.948,
    "prob_over_2_5": 0.887,
    "prob_btts": 0.49,
    "predicted_score_home": 4,
    "predicted_score_away": 0,
    "is_over_1_5_alert": 1,
    "is_over_2_5_alert": 1,
    "real_score_home": 6,
    "real_score_away": 0
  },
  {
    "match_number": 28,
    "date": "2026-06-18",
    "kickoff_utc": "2026-06-19T01:00:00Z",
    "group": "A",
    "home_team": "Mexico",
    "away_team": "South Korea",
    "expected_goals_home": 1.4,
    "expected_goals_away": 0.77,
    "prob_win_home": 0.521,
    "prob_draw": 0.275,
    "prob_win_away": 0.205,
    "prob_over_1_5": 0.637,
    "prob_over_2_5": 0.368,
    "prob_btts": 0.403,
    "predicted_score_home": 1,
    "predicted_score_away": 0,
    "is_over_1_5_alert": 0,
    "is_over_2_5_alert": 0,
    "real_score_home": 1,
    "real_score_away": 0
  },
  {
    "match_number": 29,
    "date": "2026-06-19",
    "kickoff_utc": "2026-06-20T01:00:00Z",
    "group": "C",
    "home_team": "Brazil",
    "away_team": "Haiti",
    "expected_goals_home": 4.71,
    "expected_goals_away": 0.78,
    "prob_win_home": 0.939,
    "prob_draw": 0.041,
    "prob_win_away": 0.019,
    "prob_over_1_5": 0.951,
    "prob_over_2_5": 0.889,
    "prob_btts": 0.526,
    "predicted_score_home": 4,
    "predicted_score_away": 0,
    "is_over_1_5_alert": 1,
    "is_over_2_5_alert": 1,
    "real_score_home": 3,
    "real_score_away": 0
  },
  {
    "match_number": 30,
    "date": "2026-06-19",
    "kickoff_utc": "2026-06-19T22:00:00Z",
    "group": "C",
    "home_team": "Scotland",
    "away_team": "Morocco",
    "expected_goals_home": 0.58,
    "expected_goals_away": 2.95,
    "prob_win_home": 0.047,
    "prob_draw": 0.106,
    "prob_win_away": 0.848,
    "prob_over_1_5": 0.867,
    "prob_over_2_5": 0.685,
    "prob_btts": 0.418,
    "predicted_score_home": 0,
    "predicted_score_away": 2,
    "is_over_1_5_alert": 1,
    "is_over_2_5_alert": 0,
    "real_score_home": 0,
    "real_score_away": 1
  },
  {
    "match_number": 31,
    "date": "2026-06-19",
    "kickoff_utc": "2026-06-20T03:00:00Z",
    "group": "D",
    "home_team": "Turkey",
    "away_team": "Paraguay",
    "expected_goals_home": 1.77,
    "expected_goals_away": 1.05,
    "prob_win_home": 0.542,
    "prob_draw": 0.234,
    "prob_win_away": 0.224,
    "prob_over_1_5": 0.773,
    "prob_over_2_5": 0.537,
    "prob_btts": 0.541,
    "predicted_score_home": 1,
    "predicted_score_away": 1,
    "is_over_1_5_alert": 0,
    "is_over_2_5_alert": 0,
    "real_score_home": 0,
    "real_score_away": 1
  },
  {
    "match_number": 32,
    "date": "2026-06-19",
    "kickoff_utc": "2026-06-19T19:00:00Z",
    "group": "D",
    "home_team": "United States",
    "away_team": "Australia",
    "expected_goals_home": 1.73,
    "expected_goals_away": 1.45,
    "prob_win_home": 0.443,
    "prob_draw": 0.233,
    "prob_win_away": 0.324,
    "prob_over_1_5": 0.827,
    "prob_over_2_5": 0.617,
    "prob_btts": 0.63,
    "predicted_score_home": 1,
    "predicted_score_away": 1,
    "is_over_1_5_alert": 0,
    "is_over_2_5_alert": 0,
    "real_score_home": 2,
    "real_score_away": 0
  },
  {
    "match_number": 33,
    "date": "2026-06-20",
    "kickoff_utc": "2026-06-20T20:00:00Z",
    "group": "E",
    "home_team": "Germany",
    "away_team": "Ivory Coast",
    "expected_goals_home": 1.6,
    "expected_goals_away": 1.3,
    "prob_win_home": 0.444,
    "prob_draw": 0.245,
    "prob_win_away": 0.311,
    "prob_over_1_5": 0.784,
    "prob_over_2_5": 0.552,
    "prob_btts": 0.579,
    "predicted_score_home": 1,
    "predicted_score_away": 1,
    "is_over_1_5_alert": 0,
    "is_over_2_5_alert": 0,
    "real_score_home": 2,
    "real_score_away": 1
  },
  {
    "match_number": 34,
    "date": "2026-06-20",
    "kickoff_utc": "2026-06-21T00:00:00Z",
    "group": "E",
    "home_team": "Ecuador",
    "away_team": "Curaçao",
    "expected_goals_home": 1.9,
    "expected_goals_away": 0.46,
    "prob_win_home": 0.722,
    "prob_draw": 0.197,
    "prob_win_away": 0.081,
    "prob_over_1_5": 0.684,
    "prob_over_2_5": 0.421,
    "prob_btts": 0.315,
    "predicted_score_home": 1,
    "predicted_score_away": 0,
    "is_over_1_5_alert": 0,
    "is_over_2_5_alert": 0,
    "real_score_home": 0,
    "real_score_away": 0
  },
  {
    "match_number": 35,
    "date": "2026-06-20",
    "kickoff_utc": "2026-06-20T17:00:00Z",
    "group": "F",
    "home_team": "Netherlands",
    "away_team": "Sweden",
    "expected_goals_home": 4.86,
    "expected_goals_away": 1.62,
    "prob_win_home": 0.861,
    "prob_draw": 0.075,
    "prob_win_away": 0.065,
    "prob_over_1_5": 0.961,
    "prob_over_2_5": 0.929,
    "prob_btts": 0.775,
    "predicted_score_home": 4,
    "predicted_score_away": 1,
    "is_over_1_5_alert": 1,
    "is_over_2_5_alert": 1,
    "real_score_home": 5,
    "real_score_away": 1
  },
  {
    "match_number": 36,
    "date": "2026-06-20",
    "kickoff_utc": "2026-06-21T04:00:00Z",
    "group": "F",
    "home_team": "Tunisia",
    "away_team": "Japan",
    "expected_goals_home": 0.65,
    "expected_goals_away": 4.3,
    "prob_win_home": 0.019,
    "prob_draw": 0.047,
    "prob_win_away": 0.934,
    "prob_over_1_5": 0.945,
    "prob_over_2_5": 0.858,
    "prob_btts": 0.465,
    "predicted_score_home": 0,
    "predicted_score_away": 4,
    "is_over_1_5_alert": 1,
    "is_over_2_5_alert": 1,
    "real_score_home": 0,
    "real_score_away": 4
  },
  {
    "match_number": 37,
    "date": "2026-06-21",
    "kickoff_utc": "2026-06-21T22:00:00Z",
    "group": "H",
    "home_team": "Uruguay",
    "away_team": "Cape Verde",
    "expected_goals_home": 1.67,
    "expected_goals_away": 0.61,
    "prob_win_home": 0.633,
    "prob_draw": 0.236,
    "prob_win_away": 0.131,
    "prob_over_1_5": 0.664,
    "prob_over_2_5": 0.398,
    "prob_btts": 0.369,
    "predicted_score_home": 1,
    "predicted_score_away": 0,
    "is_over_1_5_alert": 0,
    "is_over_2_5_alert": 0,
    "real_score_home": 2,
    "real_score_away": 2
  },
  {
    "match_number": 38,
    "date": "2026-06-21",
    "kickoff_utc": "2026-06-21T16:00:00Z",
    "group": "H",
    "home_team": "Spain",
    "away_team": "Saudi Arabia",
    "expected_goals_home": 4.58,
    "expected_goals_away": 0.38,
    "prob_win_home": 0.967,
    "prob_draw": 0.026,
    "prob_win_away": 0.007,
    "prob_over_1_5": 0.939,
    "prob_over_2_5": 0.853,
    "prob_btts": 0.31,
    "predicted_score_home": 4,
    "predicted_score_away": 0,
    "is_over_1_5_alert": 1,
    "is_over_2_5_alert": 1,
    "real_score_home": 4,
    "real_score_away": 0
  },
  {
    "match_number": 39,
    "date": "2026-06-21",
    "kickoff_utc": "2026-06-21T19:00:00Z",
    "group": "G",
    "home_team": "Belgium",
    "away_team": "Iran",
    "expected_goals_home": 2.54,
    "expected_goals_away": 1.09,
    "prob_win_home": 0.687,
    "prob_draw": 0.17,
    "prob_win_away": 0.144,
    "prob_over_1_5": 0.877,
    "prob_over_2_5": 0.703,
    "prob_btts": 0.613,
    "predicted_score_home": 2,
    "predicted_score_away": 1,
    "is_over_1_5_alert": 1,
    "is_over_2_5_alert": 1,
    "real_score_home": 0,
    "real_score_away": 0
  },
  {
    "match_number": 40,
    "date": "2026-06-21",
    "kickoff_utc": "2026-06-22T01:00:00Z",
    "group": "G",
    "home_team": "New Zealand",
    "away_team": "Egypt",
    "expected_goals_home": 1.27,
    "expected_goals_away": 2.62,
    "prob_win_home": 0.166,
    "prob_draw": 0.171,
    "prob_win_away": 0.663,
    "prob_over_1_5": 0.9,
    "prob_over_2_5": 0.745,
    "prob_btts": 0.667,
    "predicted_score_home": 1,
    "predicted_score_away": 2,
    "is_over_1_5_alert": 1,
    "is_over_2_5_alert": 1,
    "real_score_home": 1,
    "real_score_away": 3
  },
  {
    "match_number": 41,
    "date": "2026-06-22",
    "kickoff_utc": "2026-06-23T00:00:00Z",
    "group": "I",
    "home_team": "Norway",
    "away_team": "Senegal",
    "expected_goals_home": 2.61,
    "expected_goals_away": 2.23,
    "prob_win_home": 0.476,
    "prob_draw": 0.184,
    "prob_win_away": 0.34,
    "prob_over_1_5": 0.953,
    "prob_over_2_5": 0.861,
    "prob_btts": 0.826,
    "predicted_score_home": 2,
    "predicted_score_away": 2,
    "is_over_1_5_alert": 1,
    "is_over_2_5_alert": 1,
    "real_score_home": 3,
    "real_score_away": 2
  },
  {
    "match_number": 42,
    "date": "2026-06-22",
    "kickoff_utc": "2026-06-22T21:00:00Z",
    "group": "I",
    "home_team": "France",
    "away_team": "Iraq",
    "expected_goals_home": 5.81,
    "expected_goals_away": 0.48,
    "prob_win_home": 0.983,
    "prob_draw": 0.013,
    "prob_win_away": 0.004,
    "prob_over_1_5": 0.915,
    "prob_over_2_5": 0.878,
    "prob_btts": 0.354,
    "predicted_score_home": 5,
    "predicted_score_away": 0,
    "is_over_1_5_alert": 1,
    "is_over_2_5_alert": 1,
    "real_score_home": 3,
    "real_score_away": 0
  },
  {
    "match_number": 43,
    "date": "2026-06-22",
    "kickoff_utc": "2026-06-22T17:00:00Z",
    "group": "J",
    "home_team": "Argentina",
    "away_team": "Austria",
    "expected_goals_home": 2.51,
    "expected_goals_away": 0.7,
    "prob_win_home": 0.769,
    "prob_draw": 0.149,
    "prob_win_away": 0.082,
    "prob_over_1_5": 0.83,
    "prob_over_2_5": 0.622,
    "prob_btts": 0.462,
    "predicted_score_home": 2,
    "predicted_score_away": 0,
    "is_over_1_5_alert": 0,
    "is_over_2_5_alert": 0,
    "real_score_home": 2,
    "real_score_away": 0
  },
  {
    "match_number": 44,
    "date": "2026-06-22",
    "kickoff_utc": "2026-06-23T03:00:00Z",
    "group": "J",
    "home_team": "Jordan",
    "away_team": "Algeria",
    "expected_goals_home": 1.21,
    "expected_goals_away": 3.43,
    "prob_win_home": 0.094,
    "prob_draw": 0.117,
    "prob_win_away": 0.79,
    "prob_over_1_5": 0.943,
    "prob_over_2_5": 0.839,
    "prob_btts": 0.678,
    "predicted_score_home": 1,
    "predicted_score_away": 3,
    "is_over_1_5_alert": 1,
    "is_over_2_5_alert": 1,
    "real_score_home": 1,
    "real_score_away": 2
  },
  {
    "match_number": 45,
    "date": "2026-06-23",
    "kickoff_utc": "2026-06-23T20:00:00Z",
    "group": "L",
    "home_team": "England",
    "away_team": "Ghana",
    "expected_goals_home": 2.59,
    "expected_goals_away": 0.43,
    "prob_win_home": 0.836,
    "prob_draw": 0.121,
    "prob_win_away": 0.043,
    "prob_over_1_5": 0.805,
    "prob_over_2_5": 0.583,
    "prob_btts": 0.326,
    "predicted_score_home": 2,
    "predicted_score_away": 0,
    "is_over_1_5_alert": 0,
    "is_over_2_5_alert": 0,
    "real_score_home": 0,
    "real_score_away": 0
  },
  {
    "match_number": 46,
    "date": "2026-06-23",
    "kickoff_utc": "2026-06-23T23:00:00Z",
    "group": "L",
    "home_team": "Panama",
    "away_team": "Croatia",
    "expected_goals_home": 0.99,
    "expected_goals_away": 3.11,
    "prob_win_home": 0.086,
    "prob_draw": 0.123,
    "prob_win_away": 0.791,
    "prob_over_1_5": 0.914,
    "prob_over_2_5": 0.774,
    "prob_btts": 0.598,
    "predicted_score_home": 0,
    "predicted_score_away": 3,
    "is_over_1_5_alert": 1,
    "is_over_2_5_alert": 1,
    "real_score_home": 0,
    "real_score_away": 1
  },
  {
    "match_number": 47,
    "date": "2026-06-23",
    "kickoff_utc": "2026-06-23T17:00:00Z",
    "group": "K",
    "home_team": "Portugal",
    "away_team": "Uzbekistan",
    "expected_goals_home": 4.67,
    "expected_goals_away": 0.67,
    "prob_win_home": 0.948,
    "prob_draw": 0.037,
    "prob_win_away": 0.015,
    "prob_over_1_5": 0.948,
    "prob_over_2_5": 0.88,
    "prob_btts": 0.472,
    "predicted_score_home": 4,
    "predicted_score_away": 0,
    "is_over_1_5_alert": 1,
    "is_over_2_5_alert": 1,
    "real_score_home": 5,
    "real_score_away": 0
  },
  {
    "match_number": 48,
    "date": "2026-06-23",
    "kickoff_utc": "2026-06-24T02:00:00Z",
    "group": "K",
    "home_team": "Colombia",
    "away_team": "DR Congo",
    "expected_goals_home": 1.37,
    "expected_goals_away": 0.82,
    "prob_win_home": 0.499,
    "prob_draw": 0.278,
    "prob_win_away": 0.224,
    "prob_over_1_5": 0.643,
    "prob_over_2_5": 0.374,
    "prob_btts": 0.417,
    "predicted_score_home": 1,
    "predicted_score_away": 0,
    "is_over_1_5_alert": 0,
    "is_over_2_5_alert": 0,
    "real_score_home": 1,
    "real_score_away": 0
  },
  {
    "match_number": 49,
    "date": "2026-06-24",
    "kickoff_utc": "2026-06-24T22:00:00Z",
    "group": "C",
    "home_team": "Scotland",
    "away_team": "Brazil",
    "expected_goals_home": 0.9,
    "expected_goals_away": 2.77,
    "prob_win_home": 0.095,
    "prob_draw": 0.142,
    "prob_win_away": 0.764,
    "prob_over_1_5": 0.88,
    "prob_over_2_5": 0.707,
    "prob_btts": 0.554,
    "predicted_score_home": 0,
    "predicted_score_away": 2,
    "is_over_1_5_alert": 1,
    "is_over_2_5_alert": 1,
    "real_score_home": 0,
    "real_score_away": 3
  },
  {
    "match_number": 50,
    "date": "2026-06-24",
    "kickoff_utc": "2026-06-24T22:00:00Z",
    "group": "C",
    "home_team": "Morocco",
    "away_team": "Haiti",
    "expected_goals_home": 5.03,
    "expected_goals_away": 0.51,
    "prob_win_home": 0.969,
    "prob_draw": 0.023,
    "prob_win_away": 0.007,
    "prob_over_1_5": 0.941,
    "prob_over_2_5": 0.881,
    "prob_btts": 0.383,
    "predicted_score_home": 5,
    "predicted_score_away": 0,
    "is_over_1_5_alert": 1,
    "is_over_2_5_alert": 1,
    "real_score_home": 4,
    "real_score_away": 2
  },
  {
    "match_number": 51,
    "date": "2026-06-24",
    "kickoff_utc": "2026-06-24T19:00:00Z",
    "group": "B",
    "home_team": "Switzerland",
    "away_team": "Canada",
    "expected_goals_home": 1.74,
    "expected_goals_away": 1.65,
    "prob_win_home": 0.407,
    "prob_draw": 0.227,
    "prob_win_away": 0.366,
    "prob_over_1_5": 0.852,
    "prob_over_2_5": 0.658,
    "prob_btts": 0.666,
    "predicted_score_home": 1,
    "predicted_score_away": 1,
    "is_over_1_5_alert": 1,
    "is_over_2_5_alert": 0,
    "real_score_home": 2,
    "real_score_away": 1
  },
  {
    "match_number": 52,
    "date": "2026-06-24",
    "kickoff_utc": "2026-06-24T19:00:00Z",
    "group": "B",
    "home_team": "Bosnia and Herzegovina",
    "away_team": "Qatar",
    "expected_goals_home": 3.18,
    "expected_goals_away": 1.56,
    "prob_win_home": 0.695,
    "prob_draw": 0.147,
    "prob_win_away": 0.158,
    "prob_over_1_5": 0.948,
    "prob_over_2_5": 0.849,
    "prob_btts": 0.755,
    "predicted_score_home": 3,
    "predicted_score_away": 1,
    "is_over_1_5_alert": 1,
    "is_over_2_5_alert": 1,
    "real_score_home": 3,
    "real_score_away": 1
  },
  {
    "match_number": 53,
    "date": "2026-06-24",
    "kickoff_utc": "2026-06-25T01:00:00Z",
    "group": "A",
    "home_team": "Czech Republic",
    "away_team": "Mexico",
    "expected_goals_home": 0.79,
    "expected_goals_away": 2.13,
    "prob_win_home": 0.126,
    "prob_draw": 0.191,
    "prob_win_away": 0.683,
    "prob_over_1_5": 0.788,
    "prob_over_2_5": 0.557,
    "prob_btts": 0.479,
    "predicted_score_home": 0,
    "predicted_score_away": 2,
    "is_over_1_5_alert": 0,
    "is_over_2_5_alert": 0,
    "real_score_home": 0,
    "real_score_away": 3
  },
  {
    "match_number": 54,
    "date": "2026-06-24",
    "kickoff_utc": "2026-06-25T01:00:00Z",
    "group": "A",
    "home_team": "South Africa",
    "away_team": "South Korea",
    "expected_goals_home": 0.82,
    "expected_goals_away": 2.01,
    "prob_win_home": 0.144,
    "prob_draw": 0.205,
    "prob_win_away": 0.651,
    "prob_over_1_5": 0.773,
    "prob_over_2_5": 0.536,
    "prob_btts": 0.484,
    "predicted_score_home": 0,
    "predicted_score_away": 2,
    "is_over_1_5_alert": 0,
    "is_over_2_5_alert": 0,
    "real_score_home": 1,
    "real_score_away": 0
  },
  {
    "match_number": 55,
    "date": "2026-06-25",
    "kickoff_utc": "2026-06-25T20:00:00Z",
    "group": "E",
    "home_team": "Curaçao",
    "away_team": "Ivory Coast",
    "expected_goals_home": 0.6,
    "expected_goals_away": 3.3,
    "prob_win_home": 0.037,
    "prob_draw": 0.085,
    "prob_win_away": 0.878,
    "prob_over_1_5": 0.899,
    "prob_over_2_5": 0.745,
    "prob_btts": 0.435,
    "predicted_score_home": 0,
    "predicted_score_away": 3,
    "is_over_1_5_alert": 1,
    "is_over_2_5_alert": 1,
    "real_score_home": 0,
    "real_score_away": 2
  },
  {
    "match_number": 56,
    "date": "2026-06-25",
    "kickoff_utc": "2026-06-25T20:00:00Z",
    "group": "E",
    "home_team": "Ecuador",
    "away_team": "Germany",
    "expected_goals_home": 0.75,
    "expected_goals_away": 1.23,
    "prob_win_home": 0.225,
    "prob_draw": 0.299,
    "prob_win_away": 0.476,
    "prob_over_1_5": 0.587,
    "prob_over_2_5": 0.316,
    "prob_btts": 0.372,
    "predicted_score_home": 0,
    "predicted_score_away": 1,
    "is_over_1_5_alert": 0,
    "is_over_2_5_alert": 0,
    "real_score_home": 2,
    "real_score_away": 1
  },
  {
    "match_number": 57,
    "date": "2026-06-25",
    "kickoff_utc": "2026-06-25T23:00:00Z",
    "group": "F",
    "home_team": "Japan",
    "away_team": "Sweden",
    "expected_goals_home": 4.24,
    "expected_goals_away": 1.14,
    "prob_win_home": 0.875,
    "prob_draw": 0.075,
    "prob_win_away": 0.05,
    "prob_over_1_5": 0.959,
    "prob_over_2_5": 0.892,
    "prob_btts": 0.663,
    "predicted_score_home": 4,
    "predicted_score_away": 1,
    "is_over_1_5_alert": 1,
    "is_over_2_5_alert": 1,
    "real_score_home": 1,
    "real_score_away": 1
  },
  {
    "match_number": 58,
    "date": "2026-06-25",
    "kickoff_utc": "2026-06-25T23:00:00Z",
    "group": "F",
    "home_team": "Tunisia",
    "away_team": "Netherlands",
    "expected_goals_home": 0.92,
    "expected_goals_away": 4.92,
    "prob_win_home": 0.022,
    "prob_draw": 0.042,
    "prob_win_away": 0.936,
    "prob_over_1_5": 0.951,
    "prob_over_2_5": 0.902,
    "prob_btts": 0.581,
    "predicted_score_home": 0,
    "predicted_score_away": 4,
    "is_over_1_5_alert": 1,
    "is_over_2_5_alert": 1,
    "real_score_home": 1,
    "real_score_away": 3
  },
  {
    "match_number": 59,
    "date": "2026-06-25",
    "kickoff_utc": "2026-06-26T02:00:00Z",
    "group": "D",
    "home_team": "Turkey",
    "away_team": "United States",
    "expected_goals_home": 2.36,
    "expected_goals_away": 2.4,
    "prob_win_home": 0.397,
    "prob_draw": 0.188,
    "prob_win_away": 0.414,
    "prob_over_1_5": 0.95,
    "prob_over_2_5": 0.853,
    "prob_btts": 0.823,
    "predicted_score_home": 2,
    "predicted_score_away": 2,
    "is_over_1_5_alert": 1,
    "is_over_2_5_alert": 1,
    "real_score_home": 3,
    "real_score_away": 2
  },
  {
    "match_number": 60,
    "date": "2026-06-25",
    "kickoff_utc": "2026-06-26T02:00:00Z",
    "group": "D",
    "home_team": "Paraguay",
    "away_team": "Australia",
    "expected_goals_home": 0.69,
    "expected_goals_away": 1.2,
    "prob_win_home": 0.213,
    "prob_draw": 0.304,
    "prob_win_away": 0.483,
    "prob_over_1_5": 0.564,
    "prob_over_2_5": 0.294,
    "prob_btts": 0.348,
    "predicted_score_home": 0,
    "predicted_score_away": 1,
    "is_over_1_5_alert": 0,
    "is_over_2_5_alert": 0,
    "real_score_home": 0,
    "real_score_away": 0
  },
  {
    "match_number": 61,
    "date": "2026-06-26",
    "kickoff_utc": "2026-06-26T19:00:00Z",
    "group": "I",
    "home_team": "Norway",
    "away_team": "France",
    "expected_goals_home": 2.14,
    "expected_goals_away": 3.38,
    "prob_win_home": 0.227,
    "prob_draw": 0.154,
    "prob_win_away": 0.619,
    "prob_over_1_5": 0.971,
    "prob_over_2_5": 0.91,
    "prob_btts": 0.85,
    "predicted_score_home": 2,
    "predicted_score_away": 3,
    "is_over_1_5_alert": 1,
    "is_over_2_5_alert": 1,
    "real_score_home": 1,
    "real_score_away": 4
  },
  {
    "match_number": 62,
    "date": "2026-06-26",
    "kickoff_utc": "2026-06-26T19:00:00Z",
    "group": "I",
    "home_team": "Senegal",
    "away_team": "Iraq",
    "expected_goals_home": 3.83,
    "expected_goals_away": 0.59,
    "prob_win_home": 0.917,
    "prob_draw": 0.059,
    "prob_win_away": 0.024,
    "prob_over_1_5": 0.929,
    "prob_over_2_5": 0.811,
    "prob_btts": 0.432,
    "predicted_score_home": 3,
    "predicted_score_away": 0,
    "is_over_1_5_alert": 1,
    "is_over_2_5_alert": 1,
    "real_score_home": 5,
    "real_score_away": 0
  },
  {
    "match_number": 63,
    "date": "2026-06-26",
    "kickoff_utc": "2026-06-27T03:00:00Z",
    "group": "G",
    "home_team": "Egypt",
    "away_team": "Iran",
    "expected_goals_home": 1.19,
    "expected_goals_away": 1.14,
    "prob_win_home": 0.373,
    "prob_draw": 0.281,
    "prob_win_away": 0.346,
    "prob_over_1_5": 0.676,
    "prob_over_2_5": 0.412,
    "prob_btts": 0.473,
    "predicted_score_home": 1,
    "predicted_score_away": 1,
    "is_over_1_5_alert": 0,
    "is_over_2_5_alert": 0,
    "real_score_home": 1,
    "real_score_away": 1
  },
  {
    "match_number": 64,
    "date": "2026-06-26",
    "kickoff_utc": "2026-06-27T03:00:00Z",
    "group": "G",
    "home_team": "New Zealand",
    "away_team": "Belgium",
    "expected_goals_home": 1.22,
    "expected_goals_away": 5.58,
    "prob_win_home": 0.024,
    "prob_draw": 0.039,
    "prob_win_away": 0.937,
    "prob_over_1_5": 0.933,
    "prob_over_2_5": 0.908,
    "prob_btts": 0.662,
    "predicted_score_home": 1,
    "predicted_score_away": 5,
    "is_over_1_5_alert": 1,
    "is_over_2_5_alert": 1,
    "real_score_home": 1,
    "real_score_away": 5
  },
  {
    "match_number": 65,
    "date": "2026-06-26",
    "kickoff_utc": "2026-06-27T00:00:00Z",
    "group": "H",
    "home_team": "Cape Verde",
    "away_team": "Saudi Arabia",
    "expected_goals_home": 1.27,
    "expected_goals_away": 0.95,
    "prob_win_home": 0.439,
    "prob_draw": 0.284,
    "prob_win_away": 0.277,
    "prob_over_1_5": 0.651,
    "prob_over_2_5": 0.383,
    "prob_btts": 0.441,
    "predicted_score_home": 1,
    "predicted_score_away": 0,
    "is_over_1_5_alert": 0,
    "is_over_2_5_alert": 0,
    "real_score_home": 0,
    "real_score_away": 0
  },
  {
    "match_number": 66,
    "date": "2026-06-26",
    "kickoff_utc": "2026-06-27T00:00:00Z",
    "group": "H",
    "home_team": "Uruguay",
    "away_team": "Spain",
    "expected_goals_home": 0.68,
    "expected_goals_away": 2.18,
    "prob_win_home": 0.102,
    "prob_draw": 0.18,
    "prob_win_away": 0.719,
    "prob_over_1_5": 0.778,
    "prob_over_2_5": 0.543,
    "prob_btts": 0.436,
    "predicted_score_home": 0,
    "predicted_score_away": 2,
    "is_over_1_5_alert": 0,
    "is_over_2_5_alert": 0,
    "real_score_home": 0,
    "real_score_away": 1
  },
  {
    "match_number": 67,
    "date": "2026-06-27",
    "kickoff_utc": "2026-06-27T21:00:00Z",
    "group": "L",
    "home_team": "Panama",
    "away_team": "England",
    "expected_goals_home": 0.36,
    "expected_goals_away": 3.91,
    "prob_win_home": 0.011,
    "prob_draw": 0.042,
    "prob_win_away": 0.947,
    "prob_over_1_5": 0.919,
    "prob_over_2_5": 0.792,
    "prob_btts": 0.294,
    "predicted_score_home": 0,
    "predicted_score_away": 3,
    "is_over_1_5_alert": 1,
    "is_over_2_5_alert": 1,
    "real_score_home": 0,
    "real_score_away": 2
  },
  {
    "match_number": 68,
    "date": "2026-06-27",
    "kickoff_utc": "2026-06-27T21:00:00Z",
    "group": "L",
    "home_team": "Croatia",
    "away_team": "Ghana",
    "expected_goals_home": 2.06,
    "expected_goals_away": 1.19,
    "prob_win_home": 0.573,
    "prob_draw": 0.211,
    "prob_win_away": 0.216,
    "prob_over_1_5": 0.835,
    "prob_over_2_5": 0.63,
    "prob_btts": 0.608,
    "predicted_score_home": 2,
    "predicted_score_away": 1,
    "is_over_1_5_alert": 0,
    "is_over_2_5_alert": 0,
    "real_score_home": 2,
    "real_score_away": 1
  },
  {
    "match_number": 69,
    "date": "2026-06-27",
    "kickoff_utc": "2026-06-28T02:00:00Z",
    "group": "J",
    "home_team": "Algeria",
    "away_team": "Austria",
    "expected_goals_home": 1.94,
    "expected_goals_away": 2.18,
    "prob_win_home": 0.353,
    "prob_draw": 0.202,
    "prob_win_away": 0.445,
    "prob_over_1_5": 0.917,
    "prob_over_2_5": 0.779,
    "prob_btts": 0.759,
    "predicted_score_home": 1,
    "predicted_score_away": 2,
    "is_over_1_5_alert": 1,
    "is_over_2_5_alert": 1,
    "real_score_home": 3,
    "real_score_away": 3
  },
  {
    "match_number": 70,
    "date": "2026-06-27",
    "kickoff_utc": "2026-06-28T02:00:00Z",
    "group": "J",
    "home_team": "Jordan",
    "away_team": "Argentina",
    "expected_goals_home": 0.39,
    "expected_goals_away": 4.45,
    "prob_win_home": 0.008,
    "prob_draw": 0.029,
    "prob_win_away": 0.963,
    "prob_over_1_5": 0.938,
    "prob_over_2_5": 0.845,
    "prob_btts": 0.313,
    "predicted_score_home": 0,
    "predicted_score_away": 4,
    "is_over_1_5_alert": 1,
    "is_over_2_5_alert": 1,
    "real_score_home": 1,
    "real_score_away": 3
  },
  {
    "match_number": 71,
    "date": "2026-06-27",
    "kickoff_utc": "2026-06-27T23:30:00Z",
    "group": "K",
    "home_team": "Colombia",
    "away_team": "Portugal",
    "expected_goals_home": 1.27,
    "expected_goals_away": 2.16,
    "prob_win_home": 0.22,
    "prob_draw": 0.205,
    "prob_win_away": 0.576,
    "prob_over_1_5": 0.856,
    "prob_over_2_5": 0.666,
    "prob_btts": 0.637,
    "predicted_score_home": 1,
    "predicted_score_away": 2,
    "is_over_1_5_alert": 1,
    "is_over_2_5_alert": 0,
    "real_score_home": 0,
    "real_score_away": 0
  },
  {
    "match_number": 72,
    "date": "2026-06-27",
    "kickoff_utc": "2026-06-27T23:30:00Z",
    "group": "K",
    "home_team": "DR Congo",
    "away_team": "Uzbekistan",
    "expected_goals_home": 1.77,
    "expected_goals_away": 0.72,
    "prob_win_home": 0.626,
    "prob_draw": 0.227,
    "prob_win_away": 0.147,
    "prob_over_1_5": 0.71,
    "prob_over_2_5": 0.453,
    "prob_btts": 0.425,
    "predicted_score_home": 1,
    "predicted_score_away": 0,
    "is_over_1_5_alert": 0,
    "is_over_2_5_alert": 0,
    "real_score_home": 3,
    "real_score_away": 1
  }
]